CHANGES.txt
LICENSE.txt
README.txt
setup.py
version.txt
raisin/__init__.py
raisin.restish.egg-info/PKG-INFO
raisin.restish.egg-info/SOURCES.txt
raisin.restish.egg-info/dependency_links.txt
raisin.restish.egg-info/entry_points.txt
raisin.restish.egg-info/namespace_packages.txt
raisin.restish.egg-info/not-zip-safe
raisin.restish.egg-info/requires.txt
raisin.restish.egg-info/top_level.txt
raisin/restish/__init__.py
raisin/restish/wsgiapp.py