Metadata-Version: 1.0
Name: raisin.restish
Version: 1.2
Summary: A package used in the Raisin web application
Home-page: http://big.crg.cat/services/grape
Author: Maik Roder
Author-email: maikroeder@gmail.com
License: GPL
Keywords: RNA-Seq pipeline ngs transcriptome bioinformatics ETL
Platform: UNKNOWN
Classifier: Development Status :: 5 - Production/Stable
Classifier: Programming Language :: Python
Classifier: Intended Audience :: Developers
Classifier: Operating System :: OS Independent
Classifier: License :: OSI Approved :: GNU General Public License (GPL)
Classifier: Natural Language :: English
Classifier: Topic :: Software Development :: Libraries :: Python Modules
Classifier: Operating System :: POSIX :: Linux
